{ "frames": {
   "player (Layer) 0.aseprite": {
    "frame": { "x": 0, "y": 0, "w": 8, "h": 24 },
    "rotated": false,
    "trimmed": false,
    "spriteSourceSize": { "x": 0, "y": 0, "w": 8, "h": 24 },
    "sourceSize": { "w": 8, "h": 24 },
    "duration": 400
   },
   "player (Layer) 1.aseprite": {
    "frame": { "x": 8, "y": 0, "w": 8, "h": 24 },
    "rotated": false,
    "trimmed": false,
    "spriteSourceSize": { "x": 0, "y": 0, "w": 8, "h": 24 },
    "sourceSize": { "w": 8, "h": 24 },
    "duration": 200
   },
   "player (Layer) 2.aseprite": {
    "frame": { "x": 16, "y": 0, "w": 8, "h": 24 },
    "rotated": false,
    "trimmed": false,
    "spriteSourceSize": { "x": 0, "y": 0, "w": 8, "h": 24 },
    "sourceSize": { "w": 8, "h": 24 },
    "duration": 200
   },
   "player (Layer) 3.aseprite": {
    "frame": { "x": 24, "y": 0, "w": 8, "h": 24 },
    "rotated": false,
    "trimmed": false,
    "spriteSourceSize": { "x": 0, "y": 0, "w": 8, "h": 24 },
    "sourceSize": { "w": 8, "h": 24 },
    "duration": 100
   },
   "player (Layer) 4.aseprite": {
    "frame": { "x": 32, "y": 0, "w": 8, "h": 24 },
    "rotated": false,
    "trimmed": false,
    "spriteSourceSize": { "x": 0, "y": 0, "w": 8, "h": 24 },
    "sourceSize": { "w": 8, "h": 24 },
    "duration": 200
   },
   "player (Layer) 5.aseprite": {
    "frame": { "x": 40, "y": 0, "w": 8, "h": 24 },
    "rotated": false,
    "trimmed": false,
    "spriteSourceSize": { "x": 0, "y": 0, "w": 8, "h": 24 },
    "sourceSize": { "w": 8, "h": 24 },
    "duration": 100
   },
   "player (Layer) 6.aseprite": {
    "frame": { "x": 48, "y": 0, "w": 8, "h": 24 },
    "rotated": false,
    "trimmed": false,
    "spriteSourceSize": { "x": 0, "y": 0, "w": 8, "h": 24 },
    "sourceSize": { "w": 8, "h": 24 },
    "duration": 100
   },
   "player (Layer) 7.aseprite": {
    "frame": { "x": 56, "y": 0, "w": 8, "h": 24 },
    "rotated": false,
    "trimmed": false,
    "spriteSourceSize": { "x": 0, "y": 0, "w": 8, "h": 24 },
    "sourceSize": { "w": 8, "h": 24 },
    "duration": 400
   },
   "player (Layer) 8.aseprite": {
    "frame": { "x": 64, "y": 0, "w": 8, "h": 24 },
    "rotated": false,
    "trimmed": false,
    "spriteSourceSize": { "x": 0, "y": 0, "w": 8, "h": 24 },
    "sourceSize": { "w": 8, "h": 24 },
    "duration": 200
   },
   "player (Layer) 9.aseprite": {
    "frame": { "x": 72, "y": 0, "w": 8, "h": 24 },
    "rotated": false,
    "trimmed": false,
    "spriteSourceSize": { "x": 0, "y": 0, "w": 8, "h": 24 },
    "sourceSize": { "w": 8, "h": 24 },
    "duration": 200
   },
   "player (Layer) 10.aseprite": {
    "frame": { "x": 80, "y": 0, "w": 8, "h": 24 },
    "rotated": false,
    "trimmed": false,
    "spriteSourceSize": { "x": 0, "y": 0, "w": 8, "h": 24 },
    "sourceSize": { "w": 8, "h": 24 },
    "duration": 100
   },
   "player (Layer) 11.aseprite": {
    "frame": { "x": 88, "y": 0, "w": 8, "h": 24 },
    "rotated": false,
    "trimmed": false,
    "spriteSourceSize": { "x": 0, "y": 0, "w": 8, "h": 24 },
    "sourceSize": { "w": 8, "h": 24 },
    "duration": 200
   },
   "player (Layer) 12.aseprite": {
    "frame": { "x": 96, "y": 0, "w": 8, "h": 24 },
    "rotated": false,
    "trimmed": false,
    "spriteSourceSize": { "x": 0, "y": 0, "w": 8, "h": 24 },
    "sourceSize": { "w": 8, "h": 24 },
    "duration": 100
   },
   "player (Layer) 13.aseprite": {
    "frame": { "x": 104, "y": 0, "w": 8, "h": 24 },
    "rotated": false,
    "trimmed": false,
    "spriteSourceSize": { "x": 0, "y": 0, "w": 8, "h": 24 },
    "sourceSize": { "w": 8, "h": 24 },
    "duration": 100
   }
 },
 "meta": {
  "app": "http://www.aseprite.org/",
  "version": "1.2.24-x64",
  "image": "player.png",
  "format": "RGBA8888",
  "size": { "w": 112, "h": 24 },
  "scale": "1",
  "frameTags": [
   { "name": "idle", "from": 0, "to": 1, "direction": "forward" },
   { "name": "run", "from": 2, "to": 5, "direction": "forward" },
   { "name": "jump", "from": 6, "to": 6, "direction": "forward" },
   { "name": "box_idle", "from": 7, "to": 8, "direction": "forward" },
   { "name": "box_run", "from": 9, "to": 12, "direction": "forward" },
   { "name": "box_jump", "from": 13, "to": 13, "direction": "forward" }
  ],
  "layers": [
   { "name": "Layer", "opacity": 255, "blendMode": "normal" }
  ],
  "slices": [
  ]
 }
}
